introductory-task/mattes/rtl/traffic_light/traffic_light.sv
module traffic_light (
    input logic clk,
    input logic reset,

    output logic red,
    output logic yellow,
    output logic green
);

    enum {R,RY,G,Y} state_d, state_q;

    logic [31:0] clk_count = 0;
    
    always_ff @(posedge clk) begin
        clk_count <= clk_count + 1;
        if ((state_q == R | state_q == G) & clk_count == 72000000 | state_q == Y & clk_count == 36000000 | state_q == RY & clk_count == 24000000) begin 
            clk_count <= 0;
            state_q <= state_d;
        end
        else if (reset == 0)
            state_q <= R;
        else
            state_q <= state_q;
    end

    always_comb begin
        if (state_q == R) begin
            red = 1;
            yellow = 0;
            green = 0;
        end
        else if (state_q == RY) begin
            red = 1;
            yellow = 1;
            green = 0;
        end
        else if (state_q == Y) begin
            red = 0;
            yellow = 1;
            green = 0;
        end
        else begin
            red = 0;
            yellow = 0;
            green = 1;
        end
    end

    always_comb begin
        case (state_q)
            R   :   state_d = RY;
            RY  :   state_d = G;
            G   :   state_d = Y;
            Y   :   state_d = R;
        default:
            state_d = R;
        endcase
    end

endmodule

introductory-task/mattes/rtl/traffic_light/traffic_light_tb.sv
module traffic_light_tb();
    logic clk, reset;
    logic r, y, g;

    traffic_light dut (
        .clk(clk),
        .reset(reset),
        .red(r),
        .yellow(y),
        .green(g)
    );

    always begin
        clk = 1;
        reset = 0;
        forever #1 clk = ~clk;
    end

    initial begin
        $dumpfile("traffic_light.vcd");
        $dumpvars(0, dut);

        #6;
        reset = 1;
        $display("y: %b", y);
        $strobe("y: %b", y);
        #2;
        assert({r, y, g} == 3'b110) else
          $error("Wrong output. Expected r = 1, y = 1, g = 0 but got r = %b, y = %b, g = %b", r, y, g);
        #2;
        assert({r, y, g} == 3'b001) else
          $error("Wrong output. Expected r = 0, y = 0, g = 1 but got r = %b, y = %b, g = %b", r, y, g);
        #2;
        assert({r, y, g} == 3'b010) else
          $error("Wrong output. Expected r = 0, y = 1, g = 0 but got r = %b, y = %b, g = %b", r, y, g);
        #2;
        assert({r, y, g} == 3'b100) else
          $error("Wrong output. Expected r = 1, y = 0, g = 0 but got r = %b, y = %b, g = %b", r, y, g);
        #2;
        assert({r, y, g} == 3'b110) else
          $error("Wrong output. Expected r = 1, y = 1, g = 0 but got r = %b, y = %b, g = %b", r, y, g);
        reset = 0;
        #2;
        assert({r, y, g} == 3'b100) else
          $error("Wrong output after reset. Expected r = 1, y = 0, g = 0 but got r = %b, y = %b, g = %b", r, y, g);

        reset = 1;
        #2;
        assert({r, y, g} == 3'b110) else
          $error("Wrong output. Expected r = 1, y = 1, g = 0 but got r = %b, y = %b, g = %b", r, y, g);
        #2;
        assert({r, y, g} == 3'b001) else
          $error("Wrong output. Expected r = 0, y = 0, g = 1 but got r = %b, y = %b, g = %b", r, y, g);
        #2;
        assert({r, y, g} == 3'b010) else
          $error("Wrong output. Expected r = 0, y = 1, g = 0 but got r = %b, y = %b, g = %b", r, y, g);
        #2;
        assert({r, y, g} == 3'b100) else
          $error("Wrong output. Expected r = 1, y = 0, g = 0 but got r = %b, y = %b, g = %b", r, y, g);
        #2;
        assert({r, y, g} == 3'b110) else
          $error("Wrong output. Expected r = 1, y = 1, g = 0 but got r = %b, y = %b, g = %b", r, y, g);

        #12;

        $finish;
    end

endmodule

introductory-task/mattes/rtl/traffic_light/traffic_light.vcd
$date
	Tue Oct 28 14:34:25 2025
$end
$version
	Icarus Verilog
$end
$timescale
	1s
$end
$scope module traffic_light_tb $end
$scope module dut $end
$var wire 1 ! clk $end
$var wire 1 " reset $end
$var reg 32 # clk_count [31:0] $end
$var reg 1 $ green $end
$var reg 1 % red $end
$var reg 1 & yellow $end
$var integer 32 ' state_d [31:0] $end
$var integer 32 ( state_q [31:0] $end
$upscope $end
$upscope $end
$enddefinitions $end
$comment Show the parameter values. $end
$dumpall
$end
#0
$dumpvars
b0 (
b1 '
0&
1%
0$
b1 #
0"
1!
$end
#1
0!
#2
b10 #
1!
#3
0!
#4
b11 #
1!
#5
0!
#6
b100 #
1!
1"
#7
0!
#8
b101 #
1!
#9
0!
#10
b110 #
1!
#11
0!
#12
b111 #
1!
#13
0!
#14
b1000 #
1!
#15
0!
#16
b1001 #
1!
0"
#17
0!
#18
b1010 #
1!
1"
#19
0!
#20
b1011 #
1!
#21
0!
#22
b1100 #
1!
#23
0!
#24
b1101 #
1!
#25
0!
#26
b1110 #
1!
#27
0!
#28
b1111 #
1!
#29
0!
#30
b10000 #
1!
#31
0!
#32
b10001 #
1!
#33
0!
#34
b10010 #
1!
#35
0!
#36
b10011 #
1!
#37
0!
#38
b10100 #
1!
#39
0!
#40
b10101 #
1!
