introductory-task/jennifer/rtl/traffic_light/div_clock.sv
module div_clock #(
    parameter WIDTH = 0
)(
    input logic clk, reset,
    input logic [WIDTH-1:0] max,
    output logic div_clk
);

logic [WIDTH - 1:0] counter;

logic rst;

always_ff @( posedge clk or negedge reset ) begin
    if(!reset) begin 
        counter <= 0;
        div_clk <= 0;
        rst <= 1;
    end else begin
        if(counter >= (max - 1)) begin
            counter <= 0;
            div_clk <= ~div_clk;

        end else begin
            if(rst) begin
                rst <= 0;
                div_clk <= 1;
                counter <= counter;

            end else begin 
                rst <= rst;
                div_clk <= div_clk;
                counter <= counter + 1;
            end
           
        end
    end
end

endmodule

introductory-task/jennifer/rtl/traffic_light/traffic_light.sv
`include "./div_clock.sv"

module traffic_light (
    input logic clk,
    input logic reset,

    output logic red,
    output logic yellow,
    output logic green,
    output logic tone
);

    logic [25:0] max_le_cycles;
    logic [11:0] max_sp_cycles;
    logic div_clk;
    logic rst;

    div_clock #(.WIDTH(26)) div_clk_m (
        .clk(clk), .reset(reset), .max(max_le_cycles), .div_clk(div_clk)
    );
    
    div_clock #(.WIDTH(11)) speaker_clk (
        .clk(clk), .reset(reset), .max(max_sp_cycles), .div_clk(tone)
    );

    enum bit[2:0] {state_red=1, state_red_yellow=3, state_green=4, state_yellow=2} state_d, state_q;

    always_ff @( posedge div_clk or negedge reset) begin  
        if(reset == 1'b0) begin
            state_q <= state_red;
            rst <= 1'b1;
        end else begin
            state_q <= state_d;
            rst <= 1'b0;
        end
    end

    always_comb begin 
        case(state_q) 
            state_red:
                if(rst) begin
                    state_d = state_red;
                end else begin
                    state_d = state_red_yellow;
                end

            state_red_yellow:
                state_d = state_green;

            state_green:
                state_d = state_yellow;

            state_yellow:
                state_d = state_red;

            default:
                state_d = state_red;
        endcase
    end

    always_comb begin 
        {green, yellow, red} = state_q;
    end

    //state length:
    always_comb begin
        case(state_q)
            state_red: begin
                max_le_cycles = 36000000; //append 000000, so 36000000 instead of 36
                max_sp_cycles = 160; //13636, 440 Hz (12 MHz clock speed)
            end
            state_red_yellow: begin
                max_le_cycles = 12000000;
                max_sp_cycles = 141; //12170, 493 Hz
            end
            state_green: begin
                max_le_cycles = 36000000;
                max_sp_cycles = 114; //11472, 523 Hz
            end
            state_yellow: begin
                max_le_cycles = 18000000;
                max_sp_cycles = 102; //10221, 587 Hz
            end
            default: begin
                max_le_cycles = 36000000;
                max_sp_cycles = 160; //13636, 440 Hz
            end        
        endcase
    end
endmodule

introductory-task/jennifer/rtl/traffic_light/traffic_light_tb.sv
module traffic_light_tb();
    logic clk, reset;
    logic r, y, g;
    logic tone_out;
    localparam integer cycles = 24000;

    traffic_light dut (
        .clk(clk),
        .reset(reset),
        .red(r),
        .yellow(y),
        .green(g),
        .tone(tone_out)
    );

    always begin
        clk = 1;
        reset = 0;
        forever #1 clk = ~clk;
    end

    initial begin
        $dumpfile("traffic_light.vcd");
        $dumpvars(0, dut);

        #6;
        reset = 1;
        #(6*cycles);
        assert({r, y, g} == 3'b110) else
          $error("Wrong output. Expected r = 1, y = 1, g = 0 but got r = %b, y = %b, g = %b", r, y, g);
        #(2*cycles);
        assert({r, y, g} == 3'b001) else
          $error("Wrong output. Expected r = 0, y = 0, g = 1 but got r = %b, y = %b, g = %b", r, y, g);
        #(6*cycles);
        assert({r, y, g} == 3'b010) else
          $error("Wrong output. Expected r = 0, y = 1, g = 0 but got r = %b, y = %b, g = %b", r, y, g);
        #(3*cycles);
        assert({r, y, g} == 3'b100) else
          $error("Wrong output. Expected r = 1, y = 0, g = 0 but got r = %b, y = %b, g = %b", r, y, g);
        #(6*cycles);
        assert({r, y, g} == 3'b110) else
          $error("Wrong output. Expected r = 1, y = 1, g = 0 but got r = %b, y = %b, g = %b", r, y, g);

        reset = 0;
        #(12*cycles);
        assert({r, y, g} == 3'b100) else
          $error("Wrong output after reset. Expected r = 1, y = 0, g = 0 but got r = %b, y = %b, g = %b", r, y, g);

        reset = 1;
        #(6*cycles);
        assert({r, y, g} == 3'b110) else
          $error("Wrong output. Expected r = 1, y = 1, g = 0 but got r = %b, y = %b, g = %b", r, y, g);
        #(2*cycles);
        assert({r, y, g} == 3'b001) else
          $error("Wrong output. Expected r = 0, y = 0, g = 1 but got r = %b, y = %b, g = %b", r, y, g);
        #(6*cycles);
        assert({r, y, g} == 3'b010) else
          $error("Wrong output. Expected r = 0, y = 1, g = 0 but got r = %b, y = %b, g = %b", r, y, g);
        #(3*cycles);
        assert({r, y, g} == 3'b100) else
          $error("Wrong output. Expected r = 1, y = 0, g = 0 but got r = %b, y = %b, g = %b", r, y, g);
        #(6*cycles);
        assert({r, y, g} == 3'b110) else
          $error("Wrong output. Expected r = 1, y = 1, g = 0 but got r = %b, y = %b, g = %b", r, y, g);

        #(12*cycles);

        $finish;
    end

endmodule

introductory-task/jennifer/rtl/traffic_light/traffic_light.vcd
$date
	Fri Oct 31 13:10:32 2025
$end
$version
	Icarus Verilog
$end
$timescale
	1s
$end
$scope module traffic_light_tb $end
$scope module dut $end
$var wire 1 ! clk $end
$var wire 1 " reset $end
$var wire 1 # tone $end
$var wire 1 $ div_clk $end
$var reg 1 % green $end
$var reg 26 & max_le_cycles [25:0] $end
$var reg 12 ' max_sp_cycles [11:0] $end
$var reg 1 ( red $end
$var reg 1 ) rst $end
$var reg 1 * yellow $end
$var reg 3 + state_d [2:0] $end
$var reg 3 , state_q [2:0] $end
$scope module div_clk_m $end
$var wire 1 ! clk $end
$var wire 26 - max [25:0] $end
$var wire 1 " reset $end
$var parameter 32 . WIDTH $end
$var reg 26 / counter [25:0] $end
$var reg 1 $ div_clk $end
$var reg 1 0 rst $end
$upscope $end
$scope module speaker_clk $end
$var wire 1 ! clk $end
$var wire 24 1 max [23:0] $end
$var wire 1 " reset $end
$var parameter 32 2 WIDTH $end
$var reg 24 3 counter [23:0] $end
$var reg 1 # div_clk $end
$var reg 1 4 rst $end
$upscope $end
$upscope $end
$upscope $end
$enddefinitions $end
$comment Show the parameter values. $end
$dumpall
b11000 2
b11010 .
$end
#0
$dumpvars
14
b0 3
b111010010000 1
10
b0 /
b10001001010101000100000000 -
b1 ,
b1 +
0*
1)
1(
b111010010000 '
b10001001010101000100000000 &
0%
0$
0#
0"
1!
$end
#1
0!
#2
1!
#3
0!
#4
1!
#5
0!
#6
b11 +
0)
1#
04
1$
00
1!
1"
#7
0!
#8
b1 /
b1 3
1!
#9
0!
#10
b10 3
b10 /
1!
#11
0!
#12
b11 /
b11 3
1!
#13
0!
#14
b100 3
b100 /
1!
#15
0!
#16
b101 /
b101 3
1!
#17
0!
#18
b110 3
b110 /
1!
#19
0!
#20
b111 /
b111 3
1!
#21
0!
#22
b1000 3
b1000 /
1!
#23
0!
#24
b1001 /
b1001 3
1!
#25
0!
#26
b1010 3
b1010 /
1!
#27
0!
#28
b1011 /
b1011 3
1!
#29
0!
#30
b1100 3
b1100 /
1!
#31
0!
#32
b1101 /
b1101 3
1!
#33
0!
#34
b1110 3
b1110 /
1!
#35
0!
#36
b1111 /
b1111 3
1!
#37
0!
#38
b10000 3
b10000 /
1!
#39
0!
#40
b10001 /
b10001 3
1!
#41
0!
#42
b10010 3
b10010 /
1!
#43
0!
#44
b10011 /
b10011 3
1!
#45
0!
#46
b10100 3
b10100 /
1!
#47
0!
#48
b10101 /
b10101 3
1!
#49
0!
#50
b10110 3
b10110 /
1!
#51
0!
#52
b10111 /
b10111 3
1!
#53
0!
#54
b11000 3
b11000 /
1!
#55
0!
#56
b11001 /
b11001 3
1!
#57
0!
#58
b11010 3
b11010 /
1!
#59
0!
#60
b11011 /
b11011 3
1!
#61
0!
#62
b11100 3
b11100 /
1!
#63
0!
#64
b11101 /
b11101 3
1!
#65
0!
#66
b11110 3
b11110 /
1!
#67
0!
#68
b11111 /
b11111 3
1!
#69
0!
#70
b100000 3
b100000 /
1!
#71
0!
#72
b100001 /
b100001 3
1!
#73
0!
#74
b100010 3
b100010 /
1!
#75
0!
#76
b100011 /
b100011 3
1!
#77
0!
#78
b100100 3
b100100 /
1!
#79
0!
#80
b100101 /
b100101 3
1!
#81
0!
#82
b100110 3
b100110 /
1!
#83
0!
#84
b100111 /
b100111 3
1!
#85
0!
#86
b101000 3
b101000 /
1!
#87
0!
#88
b101001 /
b101001 3
1!
#89
0!
#90
b101010 3
b101010 /
1!
#91
0!
#92
b101011 /
b101011 3
1!
#93
0!
#94
b101100 3
b101100 /
1!
#95
0!
#96
b101101 /
b101101 3
1!
#97
0!
#98
b101110 3
b101110 /
1!
#99
0!
#100
b101111 /
b101111 3
1!
#101
0!
#102
b110000 3
b110000 /
1!
#103
0!
#104
b110001 /
b110001 3
1!
#105
0!
#106
b110010 3
b110010 /
1!
#107
0!
#108
b110011 /
b110011 3
1!
#109
0!
#110
b110100 3
b110100 /
1!
#111
0!
#112
b110101 /
b110101 3
1!
#113
0!
#114
b110110 3
b110110 /
1!
#115
0!
#116
b110111 /
b110111 3
1!
#117
0!
#118
b111000 3
b111000 /
1!
#119
0!
#120
b111001 /
b111001 3
1!
#121
0!
#122
b111010 3
b111010 /
1!
#123
0!
#124
b111011 /
b111011 3
1!
#125
0!
#126
b111100 3
b111100 /
1!
#127
0!
#128
b111101 /
b111101 3
1!
#129
0!
#130
b111110 3
b111110 /
1!
#131
0!
#132
b111111 /
b111111 3
1!
#133
0!
#134
b1000000 3
b1000000 /
1!
#135
0!
#136
b1000001 /
b1000001 3
1!
#137
0!
#138
b1000010 3
b1000010 /
1!
#139
0!
#140
b1000011 /
b1000011 3
1!
#141
0!
#142
b1000100 3
b1000100 /
1!
#143
0!
#144
b1000101 /
b1000101 3
1!
#145
0!
#146
b1000110 3
b1000110 /
1!
#147
0!
#148
b1000111 /
b1000111 3
1!
#149
0!
#150
b1001000 3
b1001000 /
1!
#151
0!
#152
b1001001 /
b1001001 3
1!
#153
0!
#154
b1001010 3
b1001010 /
1!
#155
0!
#156
b1001011 /
b1001011 3
1!
#157
0!
#158
b1001100 3
b1001100 /
1!
#159
0!
#160
b1001101 /
b1001101 3
1!
#161
0!
#162
b1001110 3
b1001110 /
1!
#163
0!
#164
b1001111 /
b1001111 3
1!
#165
0!
#166
b1010000 3
b1010000 /
1!
#167
0!
#168
b1010001 /
b1010001 3
1!
#169
0!
#170
b1010010 3
b1010010 /
1!
#171
0!
#172
b1010011 /
b1010011 3
1!
#173
0!
#174
b1010100 3
b1010100 /
1!
#175
0!
#176
b1010101 /
b1010101 3
1!
#177
0!
#178
b1010110 3
b1010110 /
1!
#179
0!
#180
b1010111 /
b1010111 3
1!
#181
0!
#182
b1011000 3
b1011000 /
1!
#183
0!
#184
b1011001 /
b1011001 3
1!
#185
0!
#186
b1011010 3
b1011010 /
1!
#187
0!
#188
b1011011 /
b1011011 3
1!
#189
0!
#190
b1011100 3
b1011100 /
1!
#191
0!
#192
b1011101 /
b1011101 3
1!
#193
0!
#194
b1011110 3
b1011110 /
1!
#195
0!
#196
b1011111 /
b1011111 3
1!
#197
0!
#198
b1100000 3
b1100000 /
1!
#199
0!
#200
b1100001 /
b1100001 3
1!
#201
0!
#202
b1100010 3
b1100010 /
1!
#203
0!
#204
b1100011 /
b1100011 3
1!
#205
0!
#206
b1100100 3
b1100100 /
1!
#207
0!
#208
b1100101 /
b1100101 3
1!
#209
0!
#210
b1100110 3
b1100110 /
1!
#211
0!
#212
b1100111 /
b1100111 3
1!
#213
0!
#214
b1101000 3
b1101000 /
1!
#215
0!
#216
b1101001 /
b1101001 3
1!
#217
0!
#218
b1101010 3
b1101010 /
1!
#219
0!
#220
b1101011 /
b1101011 3
1!
#221
0!
#222
b1101100 3
b1101100 /
1!
#223
0!
#224
b1101101 /
b1101101 3
1!
#225
0!
#226
b1101110 3
b1101110 /
1!
#227
0!
#228
b1101111 /
b1101111 3
1!
#229
0!
#230
b1110000 3
b1110000 /
1!
#231
0!
#232
b1110001 /
b1110001 3
1!
#233
0!
#234
b1110010 3
b1110010 /
1!
#235
0!
#236
b1110011 /
b1110011 3
1!
#237
0!
#238
b1110100 3
b1110100 /
1!
#239
0!
#240
b1110101 /
b1110101 3
1!
#241
0!
#242
b1110110 3
b1110110 /
1!
#243
0!
#244
b1110111 /
b1110111 3
1!
#245
0!
#246
b1111000 3
b1111000 /
1!
#247
0!
#248
b1111001 /
b1111001 3
1!
#249
0!
#250
b1111010 3
b1111010 /
1!
#251
0!
#252
b1111011 /
b1111011 3
1!
#253
0!
#254
b1111100 3
b1111100 /
1!
#255
0!
#256
b1111101 /
b1111101 3
1!
#257
0!
#258
b1111110 3
b1111110 /
1!
#259
0!
#260
b1111111 /
b1111111 3
1!
#261
0!
#262
b10000000 3
b10000000 /
1!
#263
0!
#264
b10000001 /
b10000001 3
1!
#265
0!
#266
b10000010 3
b10000010 /
1!
#267
0!
#268
b10000011 /
b10000011 3
1!
#269
0!
#270
b10000100 3
b10000100 /
1!
#271
0!
#272
b10000101 /
b10000101 3
1!
#273
0!
#274
b10000110 3
b10000110 /
1!
#275
0!
#276
b10000111 /
b10000111 3
1!
#277
0!
#278
b10001000 3
b10001000 /
1!
#279
0!
#280
b10001001 /
b10001001 3
1!
#281
0!
#282
b10001010 3
b10001010 /
1!
#283
0!
#284
b10001011 /
b10001011 3
1!
#285
0!
#286
b10001100 3
b10001100 /
1!
#287
0!
#288
b10001101 /
b10001101 3
1!
#289
0!
#290
b10001110 3
b10001110 /
1!
#291
0!
#292
b10001111 /
b10001111 3
1!
#293
0!
#294
b10010000 3
b10010000 /
1!
#295
0!
#296
b10010001 /
b10010001 3
1!
#297
0!
#298
b10010010 3
b10010010 /
1!
#299
0!
#300
b10010011 /
b10010011 3
1!
#301
0!
#302
b10010100 3
b10010100 /
1!
#303
0!
#304
b10010101 /
b10010101 3
1!
#305
0!
#306
b10010110 3
b10010110 /
1!
#307
0!
#308
b10010111 /
b10010111 3
1!
#309
0!
#310
b10011000 3
b10011000 /
1!
#311
0!
#312
b10011001 /
b10011001 3
1!
#313
0!
#314
b10011010 3
b10011010 /
1!
#315
0!
#316
b10011011 /
b10011011 3
1!
#317
0!
#318
b10011100 3
b10011100 /
1!
#319
0!
#320
b10011101 /
b10011101 3
1!
#321
0!
#322
b10011110 3
b10011110 /
1!
#323
0!
#324
b10011111 /
b10011111 3
1!
#325
0!
#326
b10100000 3
b10100000 /
1!
#327
0!
#328
b10100001 /
b10100001 3
1!
#329
0!
#330
b10100010 3
b10100010 /
1!
#331
0!
#332
b10100011 /
b10100011 3
1!
#333
0!
#334
b10100100 3
b10100100 /
1!
#335
0!
#336
b10100101 /
b10100101 3
1!
#337
0!
#338
b10100110 3
b10100110 /
1!
#339
0!
#340
b10100111 /
b10100111 3
1!
#341
0!
#342
b10101000 3
b10101000 /
1!
#343
0!
#344
b10101001 /
b10101001 3
1!
#345
0!
#346
b10101010 3
b10101010 /
1!
#347
0!
#348
b10101011 /
b10101011 3
1!
#349
0!
#350
b10101100 3
b10101100 /
1!
#351
0!
#352
b10101101 /
b10101101 3
1!
#353
0!
#354
b10101110 3
b10101110 /
1!
#355
0!
#356
b10101111 /
b10101111 3
1!
#357
0!
#358
b10110000 3
b10110000 /
1!
#359
0!
#360
b10110001 /
b10110001 3
1!
#361
0!
#362
b10110010 3
b10110010 /
1!
#363
0!
#364
b10110011 /
b10110011 3
1!
#365
0!
#366
b10110100 3
b10110100 /
1!
#367
0!
#368
b10110101 /
b10110101 3
1!
#369
0!
#370
b10110110 3
b10110110 /
1!
#371
0!
#372
b10110111 /
b10110111 3
1!
#373
0!
#374
b10111000 3
b10111000 /
1!
#375
0!
#376
b10111001 /
b10111001 3
1!
#377
0!
#378
b10111010 3
b10111010 /
1!
#379
0!
#380
b10111011 /
b10111011 3
1!
#381
0!
#382
b10111100 3
b10111100 /
1!
#383
0!
#384
b10111101 /
b10111101 3
1!
#385
0!
#386
b10111110 3
b10111110 /
1!
#387
0!
#388
b10111111 /
b10111111 3
1!
#389
0!
#390
b11000000 3
b11000000 /
1!
#391
0!
#392
b11000001 /
b11000001 3
1!
#393
0!
#394
b11000010 3
b11000010 /
1!
#395
0!
#396
b11000011 /
b11000011 3
1!
#397
0!
#398
b11000100 3
b11000100 /
1!
#399
0!
#400
b11000101 /
b11000101 3
1!
#401
0!
#402
b11000110 3
b11000110 /
1!
#403
0!
#404
b11000111 /
b11000111 3
1!
#405
0!
#406
b11001000 3
b11001000 /
1!
#407
0!
#408
b11001001 /
b11001001 3
1!
#409
0!
#410
b11001010 3
b11001010 /
1!
#411
0!
#412
b11001011 /
b11001011 3
1!
#413
0!
#414
b11001100 3
b11001100 /
1!
#415
0!
#416
b11001101 /
b11001101 3
1!
#417
0!
#418
b11001110 3
b11001110 /
1!
#419
0!
#420
b11001111 /
b11001111 3
1!
#421
0!
#422
b11010000 3
b11010000 /
1!
#423
0!
#424
b11010001 /
b11010001 3
1!
#425
0!
#426
b11010010 3
b11010010 /
1!
#427
0!
#428
b11010011 /
b11010011 3
1!
#429
0!
#430
b11010100 3
b11010100 /
1!
#431
0!
#432
b11010101 /
b11010101 3
1!
#433
0!
#434
b11010110 3
b11010110 /
1!
#435
0!
#436
b11010111 /
b11010111 3
1!
#437
0!
#438
b11011000 3
b11011000 /
1!
#439
0!
#440
b11011001 /
b11011001 3
1!
#441
0!
#442
b11011010 3
b11011010 /
1!
#443
0!
#444
b11011011 /
b11011011 3
1!
#445
0!
#446
b11011100 3
b11011100 /
1!
#447
0!
#448
b11011101 /
b11011101 3
1!
#449
0!
#450
b11011110 3
b11011110 /
1!
#451
0!
#452
b11011111 /
b11011111 3
1!
#453
0!
#454
b11100000 3
b11100000 /
1!
#455
0!
#456
b11100001 /
b11100001 3
1!
#457
0!
#458
b11100010 3
b11100010 /
1!
#459
0!
#460
b11100011 /
b11100011 3
1!
#461
0!
#462
b11100100 3
b11100100 /
1!
#463
0!
#464
b11100101 /
b11100101 3
1!
#465
0!
#466
b11100110 3
b11100110 /
1!
#467
0!
#468
b11100111 /
b11100111 3
1!
#469
0!
#470
b11101000 3
b11101000 /
1!
#471
0!
#472
b11101001 /
b11101001 3
1!
#473
0!
#474
b11101010 3
b11101010 /
1!
#475
0!
#476
b11101011 /
b11101011 3
1!
#477
0!
#478
b11101100 3
b11101100 /
1!
#479
0!
#480
b11101101 /
b11101101 3
1!
#481
0!
#482
b11101110 3
b11101110 /
1!
#483
0!
#484
b11101111 /
b11101111 3
1!
#485
0!
#486
b11110000 3
b11110000 /
1!
#487
0!
#488
b11110001 /
b11110001 3
1!
#489
0!
#490
b11110010 3
b11110010 /
1!
#491
0!
#492
b11110011 /
b11110011 3
1!
#493
0!
#494
b11110100 3
b11110100 /
1!
#495
0!
#496
b11110101 /
b11110101 3
1!
#497
0!
#498
b11110110 3
b11110110 /
1!
#499
0!
#500
b11110111 /
b11110111 3
1!
#501
0!
#502
b11111000 3
b11111000 /
1!
#503
0!
#504
b11111001 /
b11111001 3
1!
#505
0!
#506
b11111010 3
b11111010 /
1!
#507
0!
#508
b11111011 /
b11111011 3
1!
#509
0!
#510
b11111100 3
b11111100 /
1!
#511
0!
#512
b11111101 /
b11111101 3
1!
#513
0!
#514
b11111110 3
b11111110 /
1!
#515
0!
#516
b11111111 /
b11111111 3
1!
#517
0!
#518
b100000000 3
b100000000 /
1!
#519
0!
#520
b100000001 /
b100000001 3
1!
#521
0!
#522
b100000010 3
b100000010 /
1!
#523
0!
#524
b100000011 /
b100000011 3
1!
#525
0!
#526
b100000100 3
b100000100 /
1!
#527
0!
#528
b100000101 /
b100000101 3
1!
#529
0!
#530
b100000110 3
b100000110 /
1!
#531
0!
#532
b100000111 /
b100000111 3
1!
#533
0!
#534
b100001000 3
b100001000 /
1!
#535
0!
#536
b100001001 /
b100001001 3
1!
#537
0!
#538
b100001010 3
b100001010 /
1!
#539
0!
#540
b100001011 /
b100001011 3
1!
#541
0!
#542
b100001100 3
b100001100 /
1!
#543
0!
#544
b100001101 /
b100001101 3
1!
#545
0!
#546
b100001110 3
b100001110 /
1!
#547
0!
#548
b100001111 /
b100001111 3
1!
#549
0!
#550
b100010000 3
b100010000 /
1!
#551
0!
#552
b100010001 /
b100010001 3
1!
#553
0!
#554
b100010010 3
b100010010 /
1!
#555
0!
#556
b100010011 /
b100010011 3
1!
#557
0!
#558
b1 +
14
0#
b0 3
10
0$
b0 /
1)
1!
0"
